odoo/addons/product_type_description2/LICENSE
odoo/addons/product_type_description2/README.rst
odoo/addons/product_type_description2/__init__.py
odoo/addons/product_type_description2/__manifest__.py
odoo/addons/product_type_description2/images/screen.png
odoo/addons/product_type_description2/models/__init__.py
odoo/addons/product_type_description2/models/product_template.py
odoo/addons/product_type_description2/static/description/icon.png
odoo/addons/product_type_description2/static/description/index.html
odoo/addons/product_type_description2/tests/TEST_INSTRUCTIONS.rst
odoo/addons/product_type_description2/views/product_template.xml
odoo_addon_product_type_description2-16.0.1.0.0.dist-info/METADATA
odoo_addon_product_type_description2-16.0.1.0.0.dist-info/WHEEL
odoo_addon_product_type_description2-16.0.1.0.0.dist-info/top_level.txt
odoo_addon_product_type_description2-16.0.1.0.0.dist-info/RECORD
